{
  "network": [
    {
      "type": "NET",
      "name": "Google DNS",
      "origin": [
        31.3113,
        -92.4451
      ],
      "dest": [
        37.4,
        -122.07
      ],
      "status": "ONLINE",
      "latency": 28.534,
      "jitter": 0.5356666666666668,
      "history": [
        27.435,
        28.323,
        27.345,
        28.089,
        28.451,
        27.851,
        27.636,
        27.735,
        27.667,
        28.534
      ],
      "ip": "8.8.8.8"
    },
    {
      "type": "NET",
      "name": "AWS Virginia",
      "origin": [
        31.3113,
        -92.4451
      ],
      "dest": [
        38.03,
        -78.5
      ],
      "status": "ONLINE",
      "latency": 81.611,
      "jitter": 2.76277777777778,
      "history": [
        79.06,
        82.814,
        77.861,
        80.569,
        77.478,
        82.418,
        79.755,
        81.273,
        80.823,
        81.611
      ],
      "ip": "52.94.76.1"
    },
    {
      "type": "NET",
      "name": "Azure East",
      "origin": [
        31.3113,
        -92.4451
      ],
      "dest": [
        36.66,
        -78.39
      ],
      "status": "ONLINE",
      "latency": 28.792,
      "jitter": 0.5509999999999999,
      "history": [
        27.517,
        28.429,
        28.462,
        28.287,
        28.376,
        28.665,
        27.589,
        28.662,
        28.071,
        28.792
      ],
      "ip": "13.107.21.200"
    },
    {
      "type": "NET",
      "name": "London Core",
      "origin": [
        31.3113,
        -92.4451
      ],
      "dest": [
        51.5,
        -0.12
      ],
      "status": "ONLINE",
      "latency": 22.313,
      "jitter": 0.4902222222222217,
      "history": [
        21.521,
        21.4,
        21.921,
        21.661,
        21.831,
        23.031,
        21.602,
        21.615,
        21.854,
        22.313
      ],
      "ip": "151.101.192.81"
    },
    {
      "type": "NET",
      "name": "Tokyo Core",
      "origin": [
        31.3113,
        -92.4451
      ],
      "dest": [
        35.67,
        139.76
      ],
      "status": "ONLINE",
      "latency": 221.782,
      "jitter": 0.8016666666666639,
      "history": [
        220.953,
        221.192,
        222.088,
        221.52,
        221.531,
        222.069,
        223.717,
        223.848,
        224.407,
        221.782
      ],
      "ip": "172.217.25.14"
    }
  ],
  "services": [
    {
      "type": "SVC",
      "name": "MY DASHBOARD",
      "url": "https://beechem.site",
      "status": "ONLINE",
      "code": 200,
      "latency": 229,
      "ssl": 82
    },
    {
      "type": "SVC",
      "name": "GITHUB API",
      "url": "https://api.github.com",
      "status": "ONLINE",
      "code": 200,
      "latency": 241,
      "ssl": 55
    }
  ],
  "synthetic": [
    {
      "name": "GOOGLE SEARCH",
      "status": "PASS",
      "latency": 1850,
      "url": "https://www.google.com"
    },
    {
      "name": "GITHUB STATUS",
      "status": "PASS",
      "latency": 2983,
      "url": "https://www.githubstatus.com"
    }
  ],
  "updated": "2025-12-12T09:00:40.089746"
}